LICENSE
README.md
src/aiuml/__init__.py
src/aiuml/cli.py
aiuml-0.0.0a0.dist-info/METADATA
aiuml-0.0.0a0.dist-info/WHEEL
aiuml-0.0.0a0.dist-info/entry_points.txt
aiuml-0.0.0a0.dist-info/licenses/LICENSE
aiuml-0.0.0a0.dist-info/RECORD
