Metadata-Version: 2.4
Name: aiuml
Version: 0.0.0a0
Summary: Reserved package name for AIUML (planning pre-release)
Project-URL: Homepage, https://aiuml.org
Project-URL: Documentation, https://aiuml.org
Project-URL: Source, https://aiuml.org
Project-URL: Issues, https://aiuml.org
Author: Jeremy Cottell
Maintainer-email: AIUML Project <team@aiuml.org>
License: MIT
License-File: LICENSE
Classifier: Development Status :: 1 - Planning
Classifier: Intended Audience :: Developers
Classifier: License :: OSI Approved :: MIT License
Classifier: Programming Language :: Python :: 3
Classifier: Topic :: Software Development :: Documentation
Requires-Python: >=3.9
